{
  "info": {
    "name": "Gestion Clinique — API Complète",
    "_postman_id": "gestion-clinique-api-v1",
    "description": "Collection complète de tous les endpoints REST du système de gestion de clinique médicale.\n\n**Ordre de test recommandé :**\n1. Auth > Register\n2. Auth > Login (copie le token automatiquement)\n3. Patients > Liste, Créer, etc.\n4. Médecins > Liste, Créer, etc.\n5. Rendez-vous > Liste, Créer, etc.\n6. Dashboard > Stats",
    "schema": "https://schema.getpostman.com/json/collection/v2.1.0/collection.json"
  },
  "variable": [
    {
      "key": "base_url",
      "value": "http://127.0.0.1:8000",
      "type": "string"
    },
    {
      "key": "token",
      "value": "",
      "type": "string",
      "description": "Token JWT — rempli automatiquement après le Login"
    },
    {
      "key": "patient_id",
      "value": "1",
      "type": "string"
    },
    {
      "key": "medecin_id",
      "value": "1",
      "type": "string"
    },
    {
      "key": "rdv_id",
      "value": "1",
      "type": "string"
    }
  ],
  "item": [
    {
      "name": "🔐 Authentification",
      "item": [
        {
          "name": "Register — Créer un compte",
          "event": [
            {
              "listen": "test",
              "script": {
                "exec": [
                  "pm.test('Status 201 Created', function () {",
                  "    pm.response.to.have.status(201);",
                  "});",
                  "pm.test('Réponse contient un token', function () {",
                  "    var json = pm.response.json();",
                  "    pm.expect(json).to.have.property('token');",
                  "    pm.collectionVariables.set('token', json.token);",
                  "});"
                ],
                "type": "text/javascript"
              }
            }
          ],
          "request": {
            "method": "POST",
            "header": [
              { "key": "Content-Type", "value": "application/json" },
              { "key": "Accept", "value": "application/json" }
            ],
            "body": {
              "mode": "raw",
              "raw": "{\n    \"username\": \"admin\",\n    \"password\": \"password123\",\n    \"role\": \"ADMIN\"\n}",
              "options": { "raw": { "language": "json" } }
            },
            "url": {
              "raw": "{{base_url}}/api/auth/register",
              "host": ["{{base_url}}"],
              "path": ["api", "auth", "register"]
            },
            "description": "Créer un nouveau compte utilisateur. Roles possibles : ADMIN, USER, MEDECIN"
          }
        },
        {
          "name": "Login — Obtenir le token JWT",
          "event": [
            {
              "listen": "test",
              "script": {
                "exec": [
                  "pm.test('Status 200 OK', function () {",
                  "    pm.response.to.have.status(200);",
                  "});",
                  "pm.test('Token JWT reçu et sauvegardé', function () {",
                  "    var json = pm.response.json();",
                  "    pm.expect(json).to.have.property('token');",
                  "    pm.collectionVariables.set('token', json.token);",
                  "    console.log('✅ Token sauvegardé automatiquement !');",
                  "});"
                ],
                "type": "text/javascript"
              }
            }
          ],
          "request": {
            "method": "POST",
            "header": [
              { "key": "Content-Type", "value": "application/json" },
              { "key": "Accept", "value": "application/json" }
            ],
            "body": {
              "mode": "raw",
              "raw": "{\n    \"username\": \"admin\",\n    \"password\": \"password123\"\n}",
              "options": { "raw": { "language": "json" } }
            },
            "url": {
              "raw": "{{base_url}}/api/auth/login",
              "host": ["{{base_url}}"],
              "path": ["api", "auth", "login"]
            },
            "description": "⚠️ Exécuter en PREMIER ! Le token est automatiquement sauvegardé dans {{token}} pour tous les tests suivants."
          }
        },
        {
          "name": "Login — Mauvais mot de passe (doit retourner 401)",
          "event": [
            {
              "listen": "test",
              "script": {
                "exec": [
                  "pm.test('Status 401 Unauthorized', function () {",
                  "    pm.response.to.have.status(401);",
                  "});",
                  "pm.test('Message erreur présent', function () {",
                  "    var json = pm.response.json();",
                  "    pm.expect(json).to.have.property('error');",
                  "});"
                ],
                "type": "text/javascript"
              }
            }
          ],
          "request": {
            "method": "POST",
            "header": [
              { "key": "Content-Type", "value": "application/json" },
              { "key": "Accept", "value": "application/json" }
            ],
            "body": {
              "mode": "raw",
              "raw": "{\n    \"username\": \"admin\",\n    \"password\": \"MAUVAIS_MOT_DE_PASSE\"\n}",
              "options": { "raw": { "language": "json" } }
            },
            "url": {
              "raw": "{{base_url}}/api/auth/login",
              "host": ["{{base_url}}"],
              "path": ["api", "auth", "login"]
            }
          }
        },
        {
          "name": "Accès sans token (doit retourner 401)",
          "event": [
            {
              "listen": "test",
              "script": {
                "exec": [
                  "pm.test('Status 401 — accès refusé sans token', function () {",
                  "    pm.response.to.have.status(401);",
                  "});"
                ],
                "type": "text/javascript"
              }
            }
          ],
          "request": {
            "method": "GET",
            "header": [
              { "key": "Accept", "value": "application/json" }
            ],
            "url": {
              "raw": "{{base_url}}/api/patients",
              "host": ["{{base_url}}"],
              "path": ["api", "patients"]
            },
            "description": "Test de sécurité : accès sans token → doit répondre 401"
          }
        },
        {
          "name": "Logout",
          "event": [
            {
              "listen": "test",
              "script": {
                "exec": [
                  "pm.test('Status 200 OK', function () {",
                  "    pm.response.to.have.status(200);",
                  "});"
                ],
                "type": "text/javascript"
              }
            }
          ],
          "request": {
            "method": "POST",
            "header": [
              { "key": "Accept", "value": "application/json" },
              { "key": "Authorization", "value": "Bearer {{token}}" }
            ],
            "url": {
              "raw": "{{base_url}}/api/auth/logout",
              "host": ["{{base_url}}"],
              "path": ["api", "auth", "logout"]
            }
          }
        }
      ]
    },
    {
      "name": "👤 Patients",
      "item": [
        {
          "name": "Créer un patient",
          "event": [
            {
              "listen": "test",
              "script": {
                "exec": [
                  "pm.test('Status 201 Created', function () {",
                  "    pm.response.to.have.status(201);",
                  "});",
                  "pm.test('Patient créé avec ID', function () {",
                  "    var json = pm.response.json();",
                  "    pm.expect(json).to.have.property('id');",
                  "    pm.collectionVariables.set('patient_id', json.id);",
                  "    console.log('Patient ID sauvegardé: ' + json.id);",
                  "});"
                ],
                "type": "text/javascript"
              }
            }
          ],
          "request": {
            "method": "POST",
            "header": [
              { "key": "Content-Type", "value": "application/json" },
              { "key": "Accept", "value": "application/json" },
              { "key": "Authorization", "value": "Bearer {{token}}" }
            ],
            "body": {
              "mode": "raw",
              "raw": "{\n    \"nom\": \"Benali\",\n    \"prenom\": \"Ahmed\",\n    \"date_naissance\": \"1990-05-15\",\n    \"cin\": \"AB123456\",\n    \"email\": \"ahmed.benali@email.com\",\n    \"telephone\": \"0612345678\",\n    \"sexe\": \"M\",\n    \"groupe_sanguin\": \"O+\",\n    \"antecedents\": \"Diabète type 2\"\n}",
              "options": { "raw": { "language": "json" } }
            },
            "url": {
              "raw": "{{base_url}}/api/patients",
              "host": ["{{base_url}}"],
              "path": ["api", "patients"]
            }
          }
        },
        {
          "name": "Liste paginée des patients",
          "event": [
            {
              "listen": "test",
              "script": {
                "exec": [
                  "pm.test('Status 200 OK', function () {",
                  "    pm.response.to.have.status(200);",
                  "});",
                  "pm.test('Réponse paginée avec data[]', function () {",
                  "    var json = pm.response.json();",
                  "    pm.expect(json).to.have.property('data');",
                  "    pm.expect(json).to.have.property('total');",
                  "    pm.expect(json).to.have.property('current_page');",
                  "});"
                ],
                "type": "text/javascript"
              }
            }
          ],
          "request": {
            "method": "GET",
            "header": [
              { "key": "Accept", "value": "application/json" },
              { "key": "Authorization", "value": "Bearer {{token}}" }
            ],
            "url": {
              "raw": "{{base_url}}/api/patients?page=1&size=10",
              "host": ["{{base_url}}"],
              "path": ["api", "patients"],
              "query": [
                { "key": "page", "value": "1" },
                { "key": "size", "value": "10" }
              ]
            }
          }
        },
        {
          "name": "Recherche patients par keyword",
          "event": [
            {
              "listen": "test",
              "script": {
                "exec": [
                  "pm.test('Status 200 OK', function () {",
                  "    pm.response.to.have.status(200);",
                  "});",
                  "pm.test('Résultats de recherche paginés', function () {",
                  "    var json = pm.response.json();",
                  "    pm.expect(json).to.have.property('data');",
                  "});"
                ],
                "type": "text/javascript"
              }
            }
          ],
          "request": {
            "method": "GET",
            "header": [
              { "key": "Accept", "value": "application/json" },
              { "key": "Authorization", "value": "Bearer {{token}}" }
            ],
            "url": {
              "raw": "{{base_url}}/api/patients?keyword=Benali&page=1&size=10",
              "host": ["{{base_url}}"],
              "path": ["api", "patients"],
              "query": [
                { "key": "keyword", "value": "Benali" },
                { "key": "page", "value": "1" },
                { "key": "size", "value": "10" }
              ]
            }
          }
        },
        {
          "name": "Détail d'un patient par ID",
          "event": [
            {
              "listen": "test",
              "script": {
                "exec": [
                  "pm.test('Status 200 OK', function () {",
                  "    pm.response.to.have.status(200);",
                  "});",
                  "pm.test('Patient a les bons champs', function () {",
                  "    var json = pm.response.json();",
                  "    pm.expect(json).to.have.property('id');",
                  "    pm.expect(json).to.have.property('nom');",
                  "    pm.expect(json).to.have.property('cin');",
                  "});"
                ],
                "type": "text/javascript"
              }
            }
          ],
          "request": {
            "method": "GET",
            "header": [
              { "key": "Accept", "value": "application/json" },
              { "key": "Authorization", "value": "Bearer {{token}}" }
            ],
            "url": {
              "raw": "{{base_url}}/api/patients/{{patient_id}}",
              "host": ["{{base_url}}"],
              "path": ["api", "patients", "{{patient_id}}"]
            }
          }
        },
        {
          "name": "Modifier un patient",
          "event": [
            {
              "listen": "test",
              "script": {
                "exec": [
                  "pm.test('Status 200 OK', function () {",
                  "    pm.response.to.have.status(200);",
                  "});",
                  "pm.test('Patient mis à jour', function () {",
                  "    var json = pm.response.json();",
                  "    pm.expect(json.telephone).to.eql('0699999999');",
                  "});"
                ],
                "type": "text/javascript"
              }
            }
          ],
          "request": {
            "method": "PUT",
            "header": [
              { "key": "Content-Type", "value": "application/json" },
              { "key": "Accept", "value": "application/json" },
              { "key": "Authorization", "value": "Bearer {{token}}" }
            ],
            "body": {
              "mode": "raw",
              "raw": "{\n    \"telephone\": \"0699999999\",\n    \"antecedents\": \"Diabète type 2, Hypertension\"\n}",
              "options": { "raw": { "language": "json" } }
            },
            "url": {
              "raw": "{{base_url}}/api/patients/{{patient_id}}",
              "host": ["{{base_url}}"],
              "path": ["api", "patients", "{{patient_id}}"]
            }
          }
        },
        {
          "name": "Supprimer un patient",
          "event": [
            {
              "listen": "test",
              "script": {
                "exec": [
                  "pm.test('Status 204 No Content', function () {",
                  "    pm.response.to.have.status(204);",
                  "});"
                ],
                "type": "text/javascript"
              }
            }
          ],
          "request": {
            "method": "DELETE",
            "header": [
              { "key": "Accept", "value": "application/json" },
              { "key": "Authorization", "value": "Bearer {{token}}" }
            ],
            "url": {
              "raw": "{{base_url}}/api/patients/{{patient_id}}",
              "host": ["{{base_url}}"],
              "path": ["api", "patients", "{{patient_id}}"]
            }
          }
        },
        {
          "name": "Patient introuvable (doit retourner 404)",
          "event": [
            {
              "listen": "test",
              "script": {
                "exec": [
                  "pm.test('Status 404 Not Found', function () {",
                  "    pm.response.to.have.status(404);",
                  "});"
                ],
                "type": "text/javascript"
              }
            }
          ],
          "request": {
            "method": "GET",
            "header": [
              { "key": "Accept", "value": "application/json" },
              { "key": "Authorization", "value": "Bearer {{token}}" }
            ],
            "url": {
              "raw": "{{base_url}}/api/patients/99999",
              "host": ["{{base_url}}"],
              "path": ["api", "patients", "99999"]
            }
          }
        }
      ]
    },
    {
      "name": "🩺 Médecins",
      "item": [
        {
          "name": "Créer un médecin",
          "event": [
            {
              "listen": "test",
              "script": {
                "exec": [
                  "pm.test('Status 201 Created', function () {",
                  "    pm.response.to.have.status(201);",
                  "});",
                  "pm.test('Médecin créé avec ID', function () {",
                  "    var json = pm.response.json();",
                  "    pm.expect(json).to.have.property('id');",
                  "    pm.collectionVariables.set('medecin_id', json.id);",
                  "});"
                ],
                "type": "text/javascript"
              }
            }
          ],
          "request": {
            "method": "POST",
            "header": [
              { "key": "Content-Type", "value": "application/json" },
              { "key": "Accept", "value": "application/json" },
              { "key": "Authorization", "value": "Bearer {{token}}" }
            ],
            "body": {
              "mode": "raw",
              "raw": "{\n    \"nom\": \"Saidi\",\n    \"prenom\": \"Lamine\",\n    \"specialite\": \"Cardiologie\",\n    \"email\": \"lamine.saidi@clinique.com\",\n    \"telephone\": \"0655555555\",\n    \"matricule\": \"MED001\",\n    \"disponible\": true\n}",
              "options": { "raw": { "language": "json" } }
            },
            "url": {
              "raw": "{{base_url}}/api/medecins",
              "host": ["{{base_url}}"],
              "path": ["api", "medecins"]
            }
          }
        },
        {
          "name": "Liste paginée des médecins",
          "event": [
            {
              "listen": "test",
              "script": {
                "exec": [
                  "pm.test('Status 200 OK', function () {",
                  "    pm.response.to.have.status(200);",
                  "});",
                  "pm.test('Réponse paginée', function () {",
                  "    var json = pm.response.json();",
                  "    pm.expect(json).to.have.property('data');",
                  "    pm.expect(json).to.have.property('total');",
                  "});"
                ],
                "type": "text/javascript"
              }
            }
          ],
          "request": {
            "method": "GET",
            "header": [
              { "key": "Accept", "value": "application/json" },
              { "key": "Authorization", "value": "Bearer {{token}}" }
            ],
            "url": {
              "raw": "{{base_url}}/api/medecins?page=1&size=10",
              "host": ["{{base_url}}"],
              "path": ["api", "medecins"],
              "query": [
                { "key": "page", "value": "1" },
                { "key": "size", "value": "10" }
              ]
            }
          }
        },
        {
          "name": "Recherche médecins par spécialité (keyword)",
          "event": [
            {
              "listen": "test",
              "script": {
                "exec": [
                  "pm.test('Status 200 OK', function () {",
                  "    pm.response.to.have.status(200);",
                  "});"
                ],
                "type": "text/javascript"
              }
            }
          ],
          "request": {
            "method": "GET",
            "header": [
              { "key": "Accept", "value": "application/json" },
              { "key": "Authorization", "value": "Bearer {{token}}" }
            ],
            "url": {
              "raw": "{{base_url}}/api/medecins?keyword=Cardio&page=1&size=10",
              "host": ["{{base_url}}"],
              "path": ["api", "medecins"],
              "query": [
                { "key": "keyword", "value": "Cardio" },
                { "key": "page", "value": "1" },
                { "key": "size", "value": "10" }
              ]
            }
          }
        },
        {
          "name": "Filtrer médecins disponibles",
          "request": {
            "method": "GET",
            "header": [
              { "key": "Accept", "value": "application/json" },
              { "key": "Authorization", "value": "Bearer {{token}}" }
            ],
            "url": {
              "raw": "{{base_url}}/api/medecins?disponible=true",
              "host": ["{{base_url}}"],
              "path": ["api", "medecins"],
              "query": [
                { "key": "disponible", "value": "true" }
              ]
            }
          }
        },
        {
          "name": "Détail d'un médecin par ID",
          "event": [
            {
              "listen": "test",
              "script": {
                "exec": [
                  "pm.test('Status 200 OK', function () {",
                  "    pm.response.to.have.status(200);",
                  "});",
                  "pm.test('Médecin a les bons champs', function () {",
                  "    var json = pm.response.json();",
                  "    pm.expect(json).to.have.property('specialite');",
                  "    pm.expect(json).to.have.property('matricule');",
                  "});"
                ],
                "type": "text/javascript"
              }
            }
          ],
          "request": {
            "method": "GET",
            "header": [
              { "key": "Accept", "value": "application/json" },
              { "key": "Authorization", "value": "Bearer {{token}}" }
            ],
            "url": {
              "raw": "{{base_url}}/api/medecins/{{medecin_id}}",
              "host": ["{{base_url}}"],
              "path": ["api", "medecins", "{{medecin_id}}"]
            }
          }
        },
        {
          "name": "Modifier un médecin",
          "event": [
            {
              "listen": "test",
              "script": {
                "exec": [
                  "pm.test('Status 200 OK', function () {",
                  "    pm.response.to.have.status(200);",
                  "});"
                ],
                "type": "text/javascript"
              }
            }
          ],
          "request": {
            "method": "PUT",
            "header": [
              { "key": "Content-Type", "value": "application/json" },
              { "key": "Accept", "value": "application/json" },
              { "key": "Authorization", "value": "Bearer {{token}}" }
            ],
            "body": {
              "mode": "raw",
              "raw": "{\n    \"disponible\": false,\n    \"telephone\": \"0677777777\"\n}",
              "options": { "raw": { "language": "json" } }
            },
            "url": {
              "raw": "{{base_url}}/api/medecins/{{medecin_id}}",
              "host": ["{{base_url}}"],
              "path": ["api", "medecins", "{{medecin_id}}"]
            }
          }
        },
        {
          "name": "Supprimer un médecin",
          "event": [
            {
              "listen": "test",
              "script": {
                "exec": [
                  "pm.test('Status 204 No Content', function () {",
                  "    pm.response.to.have.status(204);",
                  "});"
                ],
                "type": "text/javascript"
              }
            }
          ],
          "request": {
            "method": "DELETE",
            "header": [
              { "key": "Accept", "value": "application/json" },
              { "key": "Authorization", "value": "Bearer {{token}}" }
            ],
            "url": {
              "raw": "{{base_url}}/api/medecins/{{medecin_id}}",
              "host": ["{{base_url}}"],
              "path": ["api", "medecins", "{{medecin_id}}"]
            }
          }
        }
      ]
    },
    {
      "name": "📅 Rendez-vous",
      "item": [
        {
          "name": "Créer un rendez-vous",
          "event": [
            {
              "listen": "test",
              "script": {
                "exec": [
                  "pm.test('Status 201 Created', function () {",
                  "    pm.response.to.have.status(201);",
                  "});",
                  "pm.test('RDV créé avec patient et médecin', function () {",
                  "    var json = pm.response.json();",
                  "    pm.expect(json).to.have.property('id');",
                  "    pm.expect(json).to.have.property('patient');",
                  "    pm.expect(json).to.have.property('medecin');",
                  "    pm.collectionVariables.set('rdv_id', json.id);",
                  "});"
                ],
                "type": "text/javascript"
              }
            }
          ],
          "request": {
            "method": "POST",
            "header": [
              { "key": "Content-Type", "value": "application/json" },
              { "key": "Accept", "value": "application/json" },
              { "key": "Authorization", "value": "Bearer {{token}}" }
            ],
            "body": {
              "mode": "raw",
              "raw": "{\n    \"date_heure\": \"2026-04-15 10:30:00\",\n    \"statut\": \"EN_ATTENTE\",\n    \"motif\": \"Consultation cardiaque annuelle\",\n    \"notes\": \"Patient à jeun\",\n    \"patient_id\": {{patient_id}},\n    \"medecin_id\": {{medecin_id}}\n}",
              "options": { "raw": { "language": "json" } }
            },
            "url": {
              "raw": "{{base_url}}/api/rdv",
              "host": ["{{base_url}}"],
              "path": ["api", "rdv"]
            }
          }
        },
        {
          "name": "Liste paginée des rendez-vous",
          "event": [
            {
              "listen": "test",
              "script": {
                "exec": [
                  "pm.test('Status 200 OK', function () {",
                  "    pm.response.to.have.status(200);",
                  "});",
                  "pm.test('Réponse paginée avec data[]', function () {",
                  "    var json = pm.response.json();",
                  "    pm.expect(json).to.have.property('data');",
                  "});"
                ],
                "type": "text/javascript"
              }
            }
          ],
          "request": {
            "method": "GET",
            "header": [
              { "key": "Accept", "value": "application/json" },
              { "key": "Authorization", "value": "Bearer {{token}}" }
            ],
            "url": {
              "raw": "{{base_url}}/api/rdv?page=1&size=10",
              "host": ["{{base_url}}"],
              "path": ["api", "rdv"],
              "query": [
                { "key": "page", "value": "1" },
                { "key": "size", "value": "10" }
              ]
            }
          }
        },
        {
          "name": "Filtrer RDV par statut EN_ATTENTE",
          "request": {
            "method": "GET",
            "header": [
              { "key": "Accept", "value": "application/json" },
              { "key": "Authorization", "value": "Bearer {{token}}" }
            ],
            "url": {
              "raw": "{{base_url}}/api/rdv?statut=EN_ATTENTE&page=1&size=10",
              "host": ["{{base_url}}"],
              "path": ["api", "rdv"],
              "query": [
                { "key": "statut", "value": "EN_ATTENTE" },
                { "key": "page", "value": "1" },
                { "key": "size", "value": "10" }
              ]
            }
          }
        },
        {
          "name": "Filtrer RDV par médecin + statut",
          "request": {
            "method": "GET",
            "header": [
              { "key": "Accept", "value": "application/json" },
              { "key": "Authorization", "value": "Bearer {{token}}" }
            ],
            "url": {
              "raw": "{{base_url}}/api/rdv?medecinId={{medecin_id}}&statut=EN_ATTENTE&page=1",
              "host": ["{{base_url}}"],
              "path": ["api", "rdv"],
              "query": [
                { "key": "medecinId", "value": "{{medecin_id}}" },
                { "key": "statut", "value": "EN_ATTENTE" },
                { "key": "page", "value": "1" }
              ]
            }
          }
        },
        {
          "name": "Filtrer RDV par patient",
          "request": {
            "method": "GET",
            "header": [
              { "key": "Accept", "value": "application/json" },
              { "key": "Authorization", "value": "Bearer {{token}}" }
            ],
            "url": {
              "raw": "{{base_url}}/api/rdv?patientId={{patient_id}}",
              "host": ["{{base_url}}"],
              "path": ["api", "rdv"],
              "query": [
                { "key": "patientId", "value": "{{patient_id}}" }
              ]
            }
          }
        },
        {
          "name": "Filtrer RDV par date",
          "request": {
            "method": "GET",
            "header": [
              { "key": "Accept", "value": "application/json" },
              { "key": "Authorization", "value": "Bearer {{token}}" }
            ],
            "url": {
              "raw": "{{base_url}}/api/rdv?date=2026-04-15",
              "host": ["{{base_url}}"],
              "path": ["api", "rdv"],
              "query": [
                { "key": "date", "value": "2026-04-15" }
              ]
            }
          }
        },
        {
          "name": "Détail d'un rendez-vous",
          "event": [
            {
              "listen": "test",
              "script": {
                "exec": [
                  "pm.test('Status 200 OK', function () {",
                  "    pm.response.to.have.status(200);",
                  "});",
                  "pm.test('RDV contient patient et médecin', function () {",
                  "    var json = pm.response.json();",
                  "    pm.expect(json).to.have.property('patient');",
                  "    pm.expect(json).to.have.property('medecin');",
                  "    pm.expect(json).to.have.property('statut');",
                  "});"
                ],
                "type": "text/javascript"
              }
            }
          ],
          "request": {
            "method": "GET",
            "header": [
              { "key": "Accept", "value": "application/json" },
              { "key": "Authorization", "value": "Bearer {{token}}" }
            ],
            "url": {
              "raw": "{{base_url}}/api/rdv/{{rdv_id}}",
              "host": ["{{base_url}}"],
              "path": ["api", "rdv", "{{rdv_id}}"]
            }
          }
        },
        {
          "name": "Changer statut RDV → CONFIRME",
          "event": [
            {
              "listen": "test",
              "script": {
                "exec": [
                  "pm.test('Status 200 OK', function () {",
                  "    pm.response.to.have.status(200);",
                  "});",
                  "pm.test('Statut mis à jour à CONFIRME', function () {",
                  "    var json = pm.response.json();",
                  "    pm.expect(json.statut).to.eql('CONFIRME');",
                  "});"
                ],
                "type": "text/javascript"
              }
            }
          ],
          "request": {
            "method": "PUT",
            "header": [
              { "key": "Content-Type", "value": "application/json" },
              { "key": "Accept", "value": "application/json" },
              { "key": "Authorization", "value": "Bearer {{token}}" }
            ],
            "body": {
              "mode": "raw",
              "raw": "{\n    \"statut\": \"CONFIRME\"\n}",
              "options": { "raw": { "language": "json" } }
            },
            "url": {
              "raw": "{{base_url}}/api/rdv/{{rdv_id}}",
              "host": ["{{base_url}}"],
              "path": ["api", "rdv", "{{rdv_id}}"]
            }
          }
        },
        {
          "name": "Changer statut RDV → ANNULE",
          "request": {
            "method": "PUT",
            "header": [
              { "key": "Content-Type", "value": "application/json" },
              { "key": "Accept", "value": "application/json" },
              { "key": "Authorization", "value": "Bearer {{token}}" }
            ],
            "body": {
              "mode": "raw",
              "raw": "{\n    \"statut\": \"ANNULE\"\n}",
              "options": { "raw": { "language": "json" } }
            },
            "url": {
              "raw": "{{base_url}}/api/rdv/{{rdv_id}}",
              "host": ["{{base_url}}"],
              "path": ["api", "rdv", "{{rdv_id}}"]
            }
          }
        },
        {
          "name": "Supprimer un rendez-vous",
          "event": [
            {
              "listen": "test",
              "script": {
                "exec": [
                  "pm.test('Status 204 No Content', function () {",
                  "    pm.response.to.have.status(204);",
                  "});"
                ],
                "type": "text/javascript"
              }
            }
          ],
          "request": {
            "method": "DELETE",
            "header": [
              { "key": "Accept", "value": "application/json" },
              { "key": "Authorization", "value": "Bearer {{token}}" }
            ],
            "url": {
              "raw": "{{base_url}}/api/rdv/{{rdv_id}}",
              "host": ["{{base_url}}"],
              "path": ["api", "rdv", "{{rdv_id}}"]
            }
          }
        }
      ]
    },
    {
      "name": "📊 Dashboard",
      "item": [
        {
          "name": "Statistiques globales",
          "event": [
            {
              "listen": "test",
              "script": {
                "exec": [
                  "pm.test('Status 200 OK', function () {",
                  "    pm.response.to.have.status(200);",
                  "});",
                  "pm.test('Statistiques complètes présentes', function () {",
                  "    var json = pm.response.json();",
                  "    pm.expect(json).to.have.property('total_patients');",
                  "    pm.expect(json).to.have.property('total_medecins');",
                  "    pm.expect(json).to.have.property('rdv_par_statut');",
                  "    pm.expect(json).to.have.property('rdv_aujourdhui');",
                  "    pm.expect(json).to.have.property('rdv_a_venir');",
                  "    console.log('Patients: ' + json.total_patients);",
                  "    console.log('Médecins: ' + json.total_medecins);",
                  "});"
                ],
                "type": "text/javascript"
              }
            }
          ],
          "request": {
            "method": "GET",
            "header": [
              { "key": "Accept", "value": "application/json" },
              { "key": "Authorization", "value": "Bearer {{token}}" }
            ],
            "url": {
              "raw": "{{base_url}}/api/dashboard/stats",
              "host": ["{{base_url}}"],
              "path": ["api", "dashboard", "stats"]
            },
            "description": "Retourne : total_patients, total_medecins, rdv_par_statut, rdv_aujourdhui, rdv_a_venir"
          }
        }
      ]
    }
  ]
}
